appjsonify/__init__.py
appjsonify/main.py
appjsonify/modules/__init__.py
appjsonify/modules/common.py
appjsonify/modules/doc.py
appjsonify/modules/dump/__init__.py
appjsonify/modules/dump/dump.py
appjsonify/modules/edit/__init__.py
appjsonify/modules/edit/concat_columns.py
appjsonify/modules/edit/concat_pages.py
appjsonify/modules/edit/detect_sections.py
appjsonify/modules/edit/extract_captions_with_ml.py
appjsonify/modules/edit/extract_footnotes.py
appjsonify/modules/edit/extract_footnotes_with_ml.py
appjsonify/modules/edit/extract_lines.py
appjsonify/modules/edit/extract_paragraphs.py
appjsonify/modules/edit/remove_equations_with_ml.py
appjsonify/modules/edit/remove_figures_with_ml.py
appjsonify/modules/edit/remove_illegal_tokens.py
appjsonify/modules/edit/remove_lines_by_objects.py
appjsonify/modules/edit/remove_meta.py
appjsonify/modules/edit/remove_tables_with_ml.py
appjsonify/modules/edit/tailor_references.py
appjsonify/modules/load/__init__.py
appjsonify/modules/load/load.py
appjsonify/modules/load/load_objects_with_ml.py
appjsonify/modules/load/models/__init__.py
appjsonify/modules/load/models/base_model.py
appjsonify/modules/load/models/detectron2_demo/LICENSE
appjsonify/modules/load/models/detectron2_demo/README.md
appjsonify/modules/load/models/detectron2_demo/__init__.py
appjsonify/modules/load/models/detectron2_demo/demo.py
appjsonify/modules/load/models/detectron2_demo/predictor.py
appjsonify/modules/load/models/docbank.py
appjsonify/modules/load/models/publaynet.py
appjsonify/modules/load/models/tablebank.py
appjsonify/modules/runner.py
appjsonify/utils/__init__.py
appjsonify/utils/download.py
appjsonify/utils/error.py
appjsonify/utils/pipeline_checker.py
appjsonify/utils/print.py
appjsonify/utils/template.py
appjsonify/weights/.gitignore
appjsonify/weights/configs/.gitignore
appjsonify/weights/docbank/.gitignore
appjsonify/weights/docbank/X101/.gitignore
appjsonify/weights/publaynet/.gitignore
appjsonify/weights/publaynet/X101/.gitignore
appjsonify-0.1.1.dist-info/LICENSE.txt
appjsonify-0.1.1.dist-info/METADATA
appjsonify-0.1.1.dist-info/WHEEL
appjsonify-0.1.1.dist-info/entry_points.txt
appjsonify-0.1.1.dist-info/RECORD
