Metadata-Version: 2.1
Name: appjsonify
Version: 0.1.1
Summary: An academic paper PDF to JSON conversion toolkit.
Author: Atsuki Yamaguchi
Author-email: gucci.research@gmail.com
Requires-Python: >=3.10,<4.0
Classifier: Programming Language :: Python :: 3
Classifier: Programming Language :: Python :: 3.10
Classifier: Programming Language :: Python :: 3.11
Requires-Dist: opencv-python (>=4.8.0.76,<5.0.0.0)
Requires-Dist: pdf2image (>=1.16.3,<2.0.0)
Requires-Dist: pdfplumber (>=0.10.2,<0.11.0)
Requires-Dist: pillow (>=10.0.0,<11.0.0)
Requires-Dist: registrable (>=0.0.4,<0.0.5)
Requires-Dist: torch (>=2.0.1,<3.0.0)
Requires-Dist: torchaudio (>=2.0.2,<3.0.0)
Requires-Dist: torchvision (>=0.15.2,<0.16.0)
Requires-Dist: tqdm (>=4.65.0,<5.0.0)
